pyotc/__init__.py
pyotc/otc.py
pyotc/examples/__init__.py
pyotc/examples/edge_awareness.py
pyotc/examples/lollipops.py
pyotc/examples/stochastic_block_model.py
pyotc/examples/wheel.py
pyotc/otc_backend/__init__.py
pyotc/otc_backend/graph/__init__.py
pyotc/otc_backend/graph/utils.py
pyotc/otc_backend/optimal_transport/__init__.py
pyotc/otc_backend/optimal_transport/logsinkhorn.py
pyotc/otc_backend/optimal_transport/native.py
pyotc/otc_backend/optimal_transport/native_refactor.py
pyotc/otc_backend/optimal_transport/pot.py
pyotc/otc_backend/policy_iteration/__init__.py
pyotc/otc_backend/policy_iteration/utils.py
pyotc/otc_backend/policy_iteration/dense/__init__.py
pyotc/otc_backend/policy_iteration/dense/approx_tce.py
pyotc/otc_backend/policy_iteration/dense/entropic.py
pyotc/otc_backend/policy_iteration/dense/entropic_tci.py
pyotc/otc_backend/policy_iteration/dense/exact.py
pyotc/otc_backend/policy_iteration/dense/exact_tce.py
pyotc/otc_backend/policy_iteration/dense/exact_tci_lp.py
pyotc/otc_backend/policy_iteration/dense/exact_tci_pot.py
pyotc/otc_backend/policy_iteration/sparse/__init__.py
pyotc/otc_backend/policy_iteration/sparse/exact.py
pyotc/otc_backend/policy_iteration/sparse/exact_tce.py
pyotc/otc_backend/policy_iteration/sparse/exact_tci.py
pyotc-0.2.2.dist-info/METADATA
pyotc-0.2.2.dist-info/WHEEL
pyotc-0.2.2.dist-info/licenses/AUTHORS.rst
pyotc-0.2.2.dist-info/licenses/LICENSE
pyotc-0.2.2.dist-info/RECORD
