Metadata-Version: 2.4
Name: pyotc
Version: 0.2.2
Summary: Perform optimal transition coupling (OTC) in python.
Author: Jay Hineman, Yuning Pan, Bongsoo Yi
License: MIT license
License-File: AUTHORS.rst
License-File: LICENSE
Requires-Python: >=3.10
Requires-Dist: matplotlib>=3.10.0
Requires-Dist: networkx>=3.4.2
Requires-Dist: numpy>=2.2.1
Requires-Dist: pot>=0.9.5
